exacheck/__init__.py
exacheck/__version__.py
exacheck/announcer.py
exacheck/checkexecutor.py
exacheck/checkresult.py
exacheck/checkstate.py
exacheck/cli.py
exacheck/configuration.py
exacheck/exacheck.py
exacheck/exceptions/__init__.py
exacheck/exceptions/addressfamilyerror.py
exacheck/exceptions/checktimeout.py
exacheck/exceptions/dnsresolutionerror.py
exacheck/exceptions/workerprocesserror.py
exacheck/logmanager.py
exacheck/methods/__init__.py
exacheck/methods/_base.py
exacheck/methods/_remote.py
exacheck/methods/dns.py
exacheck/methods/file.py
exacheck/methods/http.py
exacheck/methods/icmp.py
exacheck/methods/ntp.py
exacheck/methods/shell.py
exacheck/methods/tcp.py
exacheck/notifications.py
exacheck/procname.py
exacheck/settings/__init__.py
exacheck/settings/_base.py
exacheck/settings/check.py
exacheck/settings/checkargs/__init__.py
exacheck/settings/checkargs/_base.py
exacheck/settings/checkargs/_remote.py
exacheck/settings/checkargs/dnsargs.py
exacheck/settings/checkargs/fileargs.py
exacheck/settings/checkargs/httpargs.py
exacheck/settings/checkargs/icmpargs.py
exacheck/settings/checkargs/ntpargs.py
exacheck/settings/checkargs/shellargs.py
exacheck/settings/checkargs/tcpargs.py
exacheck/settings/exacheck.py
exacheck/settings/loggers/__init__.py
exacheck/settings/loggers/_base.py
exacheck/settings/loggers/logfile.py
exacheck/settings/loggers/syslog.py
exacheck/settings/notifications.py
exacheck/settings/sentry.py
exacheck/settings/settings.py
exacheck/sleeper.py
exacheck/worker.py
exacheck-0.1.6.dist-info/LICENSE
exacheck-0.1.6.dist-info/METADATA
exacheck-0.1.6.dist-info/WHEEL
exacheck-0.1.6.dist-info/entry_points.txt
exacheck-0.1.6.dist-info/RECORD
