Metadata-Version: 2.3
Name: exacheck
Version: 0.1.6
Summary: ExaCheck - ExaBGP Health Checker
Keywords: bgp,exabgp,healthcheck,monitoring,network,networking,networks,routes,routing
Author: Chris
Author-email: info@exacheck.net
Requires-Python: >=3.11,<=3.14
Classifier: Development Status :: 4 - Beta
Classifier: Environment :: Console
Classifier: Framework :: Pydantic :: 2
Classifier: Intended Audience :: Information Technology
Classifier: Intended Audience :: System Administrators
Classifier: Programming Language :: Python :: 3
Classifier: Programming Language :: Python :: 3.11
Classifier: Programming Language :: Python :: 3.12
Classifier: Programming Language :: Python :: 3.13
Classifier: Topic :: System :: Monitoring
Classifier: Topic :: System :: Networking
Classifier: Topic :: System :: Networking :: Monitoring
Provides-Extra: full
Provides-Extra: sentry
Requires-Dist: apprise (>=1.9.2,<2.0.0)
Requires-Dist: click (>=8.1.8,<9.0.0)
Requires-Dist: dnspython (>=2.6.1,<3.0.0)
Requires-Dist: exabgp (>=4.2.25,<5.0.0)
Requires-Dist: httpx[http2] (>=0.28.1,<0.29.0)
Requires-Dist: icmplib (>=3.0.4,<4.0.0)
Requires-Dist: loguru (>=0.7.3,<0.8.0)
Requires-Dist: ntplib (>=0.4.0,<0.5.0)
Requires-Dist: pydantic[timezone] (>=2.11.0b1,<3.0.0)
Requires-Dist: pyyaml (>=6.0.2,<7.0.0)
Requires-Dist: sentry-sdk (>=2.22.0,<3.0.0) ; extra == "sentry" or extra == "full"
Requires-Dist: setproctitle (>=1.3.5,<2.0.0)
Requires-Dist: tabulate (>=0.9.0,<0.10.0)
Requires-Dist: ujson (>=5.10.0,<6.0.0)
Project-URL: Changelog, https://exacheck.net/development/changelog/
Project-URL: Configuration, https://exacheck.net/configuration/
Project-URL: Documentation, https://exacheck.net/deployment/
Project-URL: Docker Deployment, https://exacheck.net/deployment/docker/
Project-URL: Homepage, https://exacheck.net
Project-URL: Repository, https://github.com/exacheck/exacheck
